Archive/app.py
Archive/app2.py
Archive/app3.py
Archive/app4.py
Archive/app5.py
Archive/app6.py
Archive/app7.py
ofa_technical_task-0.1.0.dist-info/METADATA
ofa_technical_task-0.1.0.dist-info/WHEEL
ofa_technical_task-0.1.0.dist-info/top_level.txt
ofa_technical_task-0.1.0.dist-info/RECORD
