Metadata-Version: 2.4
Name: ofa-technical-task
Version: 0.1.0
Summary: This is a Streamlit application that lets you upload PDF documents, analyze their content, and interact with them using a Retrieval-Augmented Generation (RAG) chatbot.
Author-email: Sweta Javkar <swetajavkar@gmail.com>
Project-URL: Homepage, https://github.com/your-username/my-package-name
Project-URL: Issues, https://github.com/your-username/my-package-name/issues
Classifier: Programming Language :: Python :: 3
Classifier: License :: OSI Approved :: MIT License
Classifier: Operating System :: OS Independent
Requires-Python: >=3.8
Provides-Extra: dev
Requires-Dist: pytest; extra == "dev"
